mcp_slicer/__init__.py
mcp_slicer/main.py
mcp_slicer/mcp_server.py
mcp_slicer/py.typed
iflow_mcp_zhaoyouj_mcp_slicer-0.2.1.dist-info/METADATA
iflow_mcp_zhaoyouj_mcp_slicer-0.2.1.dist-info/WHEEL
iflow_mcp_zhaoyouj_mcp_slicer-0.2.1.dist-info/entry_points.txt
iflow_mcp_zhaoyouj_mcp_slicer-0.2.1.dist-info/top_level.txt
iflow_mcp_zhaoyouj_mcp_slicer-0.2.1.dist-info/RECORD
