Metadata-Version: 2.4
Name: iflow-mcp_zhaoyouj_mcp-slicer
Version: 0.2.1
Summary: A MCP server for 3D Slicer
Author: zhaoyouj
Author-email: zhaoyouj@outlook.com
License: MIT
Keywords: mcp,3d slicer,medical imaging
Classifier: Development Status :: 2 - Pre-Alpha
Classifier: Intended Audience :: Healthcare Industry
Classifier: Programming Language :: Python :: 3
Classifier: Programming Language :: Python :: 3.11
Classifier: Programming Language :: Python :: 3.12
Classifier: Programming Language :: Python :: 3.13
Classifier: License :: OSI Approved :: MIT License
Classifier: Operating System :: OS Independent
Classifier: Topic :: Scientific/Engineering :: Medical Science Apps.
Requires-Dist: mcp[cli]>=1.4.1
Requires-Dist: requests>=2.32.3
